Flask_CQLAlchemy-1.2.0.dist-info/DESCRIPTION.rst
Flask_CQLAlchemy-1.2.0.dist-info/METADATA
Flask_CQLAlchemy-1.2.0.dist-info/RECORD
Flask_CQLAlchemy-1.2.0.dist-info/WHEEL
Flask_CQLAlchemy-1.2.0.dist-info/metadata.json
Flask_CQLAlchemy-1.2.0.dist-info/top_level.txt
flask_cqlalchemy/__init__.py
